nequip_eqx/__init__.py
nequip_eqx/calculator.py
nequip_eqx/data.py
nequip_eqx/model.py
nequip_eqx/test.py
nequip_eqx/train.py
nequip_eqx-0.1.0.dist-info/METADATA
nequip_eqx-0.1.0.dist-info/WHEEL
nequip_eqx-0.1.0.dist-info/entry_points.txt
nequip_eqx-0.1.0.dist-info/licenses/LICENSE
nequip_eqx-0.1.0.dist-info/RECORD
