Metadata-Version: 2.4
Name: nequip-eqx
Version: 0.1.0
Summary: JAX implementation of the neural network interatomic potential NequIP
Project-URL: Homepage, https://pypi.org/project/nequip-eqx/
Project-URL: Repository, https://github.com/teddykoker/nequip-eqx
Author-email: Teddy Koker <teddy.koker@gmail.com>
License: MIT License
License-File: LICENSE
Requires-Python: >=3.10
Requires-Dist: ase>=3.24.0
Requires-Dist: e3nn-jax>=0.20.7
Requires-Dist: equinox>=0.11.11
Requires-Dist: jax>=0.4.34; sys_platform == 'darwin'
Requires-Dist: jax[cuda12]>=0.4.34; sys_platform == 'linux'
Requires-Dist: jraph>=0.0.6.dev0
Requires-Dist: optax>=0.2.4
Requires-Dist: pyyaml>=6.0.2
Requires-Dist: tqdm>=4.67.1
Requires-Dist: wandb>=0.19.11
